aiken_eng/__init__.py
aiken_eng/ansys.py
aiken_eng/bolts.py
aiken_eng/fatigue.py
aiken_eng/impact.py
aiken_eng/materials.py
aiken_eng/plotting.py
aiken_eng/py.typed
aiken_eng/units.py
aiken_eng-0.4.0.dist-info/WHEEL
aiken_eng-0.4.0.dist-info/METADATA
aiken_eng-0.4.0.dist-info/RECORD
