Metadata-Version: 2.3
Name: aiken-eng
Version: 0.4.0
Summary: A group of tools used by Aiken Engineering Company.
Author: eric-rudolph
Author-email: eric-rudolph <eric.rudolph@aiken-engineering.com>
Requires-Dist: matplotlib>=3.10.8
Requires-Dist: pandas>=3.0.0
Requires-Dist: ruff>=0.14.10
Requires-Dist: scipy>=1.16.3
Requires-Dist: seaborn>=0.13.2
Requires-Dist: ty>=0.0.9
Requires-Python: >=3.14
